README.md
setup.py
phone_charger/__init__.py
phone_charger/__main__.py
phone_charger/charge-phone
phone_charger/phone-charger.service
phone_charger.egg-info/PKG-INFO
phone_charger.egg-info/SOURCES.txt
phone_charger.egg-info/dependency_links.txt
phone_charger.egg-info/entry_points.txt
phone_charger.egg-info/top_level.txt