Metadata-Version: 1.1
Name: phone-charger
Version: 0.1.0
Summary: A tool to charge android phones with a usb hub
Home-page: https://github.com/matthewscholefield/phone-charger
Author: Matthew D. Scholefield
Author-email: matthew331199@gmail.com
License: UNKNOWN
Keywords: phone charger
Platform: UNKNOWN
Classifier: Development Status :: 3 - Alpha
Classifier: Intended Audience :: Developers
Classifier: Programming Language :: Python :: 3
Classifier: Programming Language :: Python :: 3.4
Classifier: Programming Language :: Python :: 3.5
Classifier: Programming Language :: Python :: 3.6
